msprime/species_trees.py
msprime/_version.py
msprime/mutations.py
msprime/__init__.py
msprime/intervals.py
msprime/core.py
msprime/cli.py
msprime/_msprimemodule.c
msprime/ancestry.py
msprime/pedigrees.py
msprime/provenance.py
msprime/likelihood.py
msprime/_msprime.cpython-312-darwin.so
msprime/demography.py
msprime/.dylibs/libgsl.28.dylib
msprime/.dylibs/libgslcblas.0.dylib
msprime-1.3.4.dist-info/RECORD
msprime-1.3.4.dist-info/WHEEL
msprime-1.3.4.dist-info/entry_points.txt
msprime-1.3.4.dist-info/top_level.txt
msprime-1.3.4.dist-info/METADATA
msprime-1.3.4.dist-info/licenses/LICENSE
