Metadata-Version: 2.4
Name: msprime
Version: 1.3.4
Summary: Simulate genealogical trees and genomic sequence data using population genetic models
Author-email: Tskit Developers <admin@tskit.dev>
License: GNU GPLv3+
Project-URL: Homepage, https://tskit.dev/msprime
Project-URL: Documentation, https://tskit.dev/msprime/docs/stable
Project-URL: Changelog, https://tskit.dev/msprime/docs/stable/CHANGELOG.html
Project-URL: Bug Tracker, https://github.com/tskit-dev/msprime/issues
Project-URL: Source Code, https://github.com/tskit-dev/msprime/
Keywords: coalescent simulation,population genetics,ms,tree sequence,tskit
Classifier: Programming Language :: C
Classifier: Programming Language :: Python
Classifier: Programming Language :: Python :: 3
Classifier: Programming Language :: Python :: 3.9
Classifier: Programming Language :: Python :: 3.10
Classifier: Programming Language :: Python :: 3.11
Classifier: Programming Language :: Python :: 3.12
Classifier: Programming Language :: Python :: 3 :: Only
Classifier: Development Status :: 5 - Production/Stable
Classifier: Environment :: Other Environment
Classifier: Intended Audience :: Science/Research
Classifier: License :: OSI Approved :: GNU General Public License v3 or later (GPLv3+)
Classifier: Operating System :: POSIX
Classifier: Operating System :: MacOS :: MacOS X
Classifier: Operating System :: Microsoft :: Windows
Classifier: Topic :: Scientific/Engineering
Classifier: Topic :: Scientific/Engineering :: Bio-Informatics
Requires-Python: >=3.9
License-File: LICENSE
Requires-Dist: numpy>=1.23.5
Requires-Dist: newick>=1.3.0
Requires-Dist: tskit>=0.5.2
Requires-Dist: demes>=0.2
Dynamic: license-file
